[
    {
        "id": "1",
        "category": [
            "Postulat"
        ],
        "name": "Prise de position - Motion Postulat (CE)",
        "relpath": "Modele_FicheAccomp_PrisePositionCEMoPo.dotx"
    },
    {
        "id": "2",
        "category": [
            "Postulat"
        ],
        "name": "Refus Motion Postulat 1",
        "relpath": "Modele_FicheAccomp_RefusMoPo1.dotx"
    },
    {
        "id": "3",
        "category": [
            "Postulat"
        ],
        "name": "Refus Motion Postulat 2",
        "relpath": "Modele_FicheAccomp_RefusMoPo2.dotx"
    },
    {
        "id": "4",
        "category": [
            "Interpellation"
        ],
        "name": "Réponse écrite - Interpellation",
        "relpath": "Modele_FicheAccomp_ReponseEcriteInterpellation.dotx"
    },
    {
        "id": "5",
        "category": [
            "Question"
        ],
        "name": "Réponse écrite - Question",
        "relpath": "Modele_FicheAccomp_ReponseEcriteQuestion1.dotx"
    },
    {
        "id": "6",
        "category": [
            "Motion"
        ],
        "name": "Position contre - Motion Postulat (CE)",
        "relpath": "Modele_PositionContre_MoPo.dotx"
    },
    {
        "id": "7",
        "category": [
            "Motion"
        ],
        "name": "Prise de position contre - Motion Postulat (CE)",
        "relpath": "Modele_PrisePositionContre_MoPo.dotx"
    },
    {
        "id": "8",
        "category": [
            "Interpellation"
        ],
        "name": "Réponse écrite - Interpellation (CE)",
        "relpath": "Modele_ReponseEcrite_Interpellation.dotx"
    },
    {
        "id": "9",
        "category": [
            "Question"
        ],
        "name": "Réponse écrite - Question (CE)",
        "relpath": "Modele_ReponseEcrite_Question.dotx"
    },
    {
        "id": "10",
        "category": [
            "Interpellation"
        ],
        "name": "Speaking note - Interpellation (CE)",
        "relpath": "Modele_SpeakingNote_Interpellation.dotx"
    },
    {
        "id": "11",
        "category": [
            "Question"
        ],
        "name": "Speaking note - Question (CE)",
        "relpath": "Modele_SpeakingNote_Question.dotx"
    },
    {
        "id": "12",
        "category": [
            "Recommandation"
        ],
        "name": "Speaking note - Recommandation (CE)",
        "relpath": "Modele_SpeakingNote_Recommandation.dotx"
    },
    {
        "id": "13",
        "category": [
            "Recommandation"
        ],
        "name": "Note (CE)",
        "relpath": "NoteCE.dotx"
    },
    {
        "id": "14",
        "category": [
            "Postulat",
            "Motion",
            "Interpellation",
            "Question",
            "Recommandation"
        ],
        "name": "Autre",
        "relpath": "NoteCE.dotx"
    },
    {
        "id": "15",
        "category": [
            "Interpellation",
            "Motion",
            "Postulat",
            "Projet de lois et décrets",
            "Question",
            "Rapport",
            "Recommandation",
            "Résolution"
        ],
        "name": "Document de base",
        "relpath": "documentBase.docx"
    },
    {
        "id": "16",
        "category": [
            "Interpellation",
            "Motion",
            "Postulat",
            "Projet de lois et décrets",
            "Question",
            "Rapport",
            "Recommandation",
            "Résolution"
        ],
        "name": "Modèle de réponse à utiliser",
        "relpath": "modeleReponse.docx"
    },
    {
        "id": "17",
        "category": [
            "Interpellation",
            "Motion",
            "Postulat",
            "Projet de lois et décrets",
            "Question",
            "Rapport",
            "Recommandation",
            "Résolution"
        ],
        "name": "Réponse écrite",
        "relpath": "reponseEcrite.docx"
    },
    {
        "id": "18",
        "category": [
            "Interpellation",
            "Motion",
            "Postulat",
            "Projet de lois et décrets",
            "Question",
            "Rapport",
            "Recommandation",
            "Résolution"
        ],
        "name": "Réponse orale",
        "relpath": "reponseOrale.docx"
    },
    {
        "id": "19",
        "category": [
            "Interpellation",
            "Motion",
            "Postulat",
            "Projet de lois et décrets",
            "Question",
            "Rapport",
            "Recommandation",
            "Résolution"
        ],
        "name": "Réponse validée",
        "relpath": "reponseValidee.docx"
    },
    {
        "id": "20",
        "category": [
            "Interpellation",
            "Motion",
            "Postulat",
            "Projet de lois et décrets",
            "Question",
            "Rapport",
            "Recommandation",
            "Résolution"
        ],
        "name": "Autre",
        "relpath": "autre.docx"
    }
]