[
  {
    "model": "ne_sop_api.Entity",
    "pk": 1,
    "fields": {
      "uuid": "1f654fec-e295-4bc2-91b8-30787f40bf81",
      "name": "Service de la chancellerie (CHAN)",
      "abbreviation": "CHAN",
      "type": 1,
      "description": "",
      "street": "Château, Rue de la Collégiale 12",
      "city": "Neuchâtel 2",
      "postalcode": "Case postale 1, 2002",
      "region": "Neuchâtel",
      "country": "Suisse",
      "website": "https://www.ne.ch/autorites/CHAN/CHAN/Pages/accueil.aspx",
      "email": "Chancellerie.Etat@ne.ch",
      "telephone": "41 32 889 40 03",
      "active": true,
      "valid": true
    }
  },
  {
    "model": "ne_sop_api.Entity",
    "pk": 7,
    "fields": {
      "uuid": "7147c965-0230-4788-a3f3-9037b5b5fb04",
      "name": "Service de la cohésion multiculturelle (COSM)",
      "abbreviation": "COSM",
      "type": 1,
      "description": "",
      "street": "Place de la Gare 6",
      "city": "La Chaux-de-Fonds",
      "postalcode": "2300",
      "region": "Neuchâtel",
      "country": "Suisse",
      "website": "https://www.ne.ch/autorites/DECS/COSM/Pages/accueil.aspx",
      "email": "cosm@ne.ch",
      "telephone": "41 32 889 74 42",
      "active": true,
      "valid": true
    }
  },
  {
    "model": "ne_sop_api.Entity",
    "pk": 2,
    "fields": {
      "uuid": "acdb88e0-64f0-4dbb-a57e-579201900741",
      "name": "Secrétariat général du DDTE (DDTE)",
      "abbreviation": "DDTE",
      "type": 1,
      "description": "",
      "street": "Château, Rue de la Collégiale 12",
      "city": "Neuchâtel 2",
      "postalcode": "Case postale 1, 2002",
      "region": "Neuchâtel",
      "country": "Suisse",
      "website": "https://www.ne.ch/autorites/ddte/sdte/Pages/accueil.aspx",
      "email": "Secretariat.DDTE@ne.ch",
      "telephone": "41 32 889 67 00",
      "active": true,
      "valid": true
    }
  },
  {
    "model": "ne_sop_api.Entity",
    "pk": 3,
    "fields": {
      "uuid": "49cee2a2-87b4-485b-9b9b-0c4ca9b5cd5c",
      "name": "Secrétariat général du DECS (DECS)",
      "abbreviation": "DECS",
      "type": 1,
      "description": "",
      "street": "Château, Rue de la Collégiale 12",
      "city": "Neuchâtel 2",
      "postalcode": "Case postale 1, 2002",
      "region": "Neuchâtel",
      "country": "Suisse",
      "website": "https://www.ne.ch/autorites/decs/secs/Pages/accueil.aspx",
      "email": "Secretariat.DECS@ne.ch",
      "telephone": "41 32 889 68 00",
      "active": true,
      "valid": true
    }
  },
  {
    "model": "ne_sop_api.Entity",
    "pk": 4,
    "fields": {
      "uuid": "4ed0aee9-1e9e-40c4-a570-680f69a9e9e0",
      "name": "Secrétariat général du DESC (DESC)",
      "abbreviation": "DESC",
      "type": 1,
      "description": "",
      "street": "Château, Rue de la Collégiale 12",
      "city": "Neuchâtel 2",
      "postalcode": "Case postale 1, 2002",
      "region": "Neuchâtel",
      "country": "Suisse",
      "website": "https://www.ne.ch/autorites/desc/sesc/Pages/accueil.aspx",
      "email": "Secretariat.DESC@ne.ch",
      "telephone": "41 32 889 61 00",
      "active": true,
      "valid": true
    }
  },
  {
    "model": "ne_sop_api.Entity",
    "pk": 5,
    "fields": {
      "uuid": "4ed0aee9-1e9e-40c4-a570-680f69a9e9e0",
      "name": "Secrétariat général du DFFD (DFFD)",
      "abbreviation": "DFFD",
      "type": 1,
      "description": "",
      "street": "Château, Rue de la Collégiale 12",
      "city": "Neuchâtel 2",
      "postalcode": "Case postale 1, 2002",
      "region": "Neuchâtel",
      "country": "Suisse",
      "website": "https://www.ne.ch/autorites/DFDS/sfds/Pages/accueil.aspx",
      "email": "Secretariat.DFFD@ne.ch",
      "telephone": "41 32 889 69 00",
      "active": true,
      "valid": true
    }
  },
  {
    "model": "ne_sop_api.Entity",
    "pk": 6,
    "fields": {
      "uuid": "c2e75cbd-d3a8-4ea1-9790-d30659af8f81",
      "name": "Secrétariat général du DSRS (DSRS)",
      "abbreviation": "DSRS",
      "type": 1,
      "description": "",
      "street": "Château, Rue de la Collégiale 12",
      "city": "Neuchâtel 2",
      "postalcode": "Case postale 1, 2002",
      "region": "Neuchâtel",
      "country": "Suisse",
      "website": "https://www.ne.ch/autorites/dfs/sdfs/Pages/accueil.aspx",
      "email": "Secretariat.DFS@ne.ch",
      "telephone": "41 32 889 64 00",
      "active": true,
      "valid": true
    }
  },
  {
    "model": "ne_sop_api.Entity",
    "pk": 8,
    "fields": {
      "uuid": "ae426d4a-8b52-4720-a180-fcbbb88b381f",
      "name": "Service de l'économie (NECO)",
      "abbreviation": "NECO",
      "type": 1,
      "description": "",
      "street": "Avenue de la Gare 2",
      "city": "Neuchâtel",
      "postalcode": "2000",
      "region": "Neuchâtel",
      "country": "Suisse",
      "website": "https://neuchateleconomie.ch/",
      "email": "neco@ne.ch",
      "telephone": "41 32 889 68 20",
      "active": true,
      "valid": true
    }
  },
  {
    "model": "ne_sop_api.Entity",
    "pk": 9,
    "fields": {
      "uuid": "e3e0b2df-1de6-46aa-8089-28a5d5c6c35c",
      "name": "Police neuchâteloise",
      "abbreviation": "PONE",
      "type": 1,
      "description": "",
      "street": "Rue des Poudrières 14",
      "city": "Neuchâtel",
      "postalcode": "Case Postale\n 2002",
      "region": "Neuchâtel",
      "country": "Suisse",
      "website": "https://www.ne.ch/autorites/desc/pone/Pages/accueil.aspx",
      "email": "Police.Neuchateloise@ne.ch",
      "telephone": "41 32 889 90 00",
      "active": true,
      "valid": true
    }
  },
  {
    "model": "ne_sop_api.Entity",
    "pk": 10,
    "fields": {
      "uuid": "e44182c1-1f72-4380-bad3-208849da680a",
      "name": "Service de l'agriculture (SAGR)",
      "abbreviation": "SAGR",
      "type": 1,
      "description": "",
      "street": "Route de l'Aurore 1",
      "city": "Cernier",
      "postalcode": "2053",
      "region": "Neuchâtel",
      "country": "Suisse",
      "website": "https://www.ne.ch/autorites/DDTE/SAGR/Pages/accueil.aspx",
      "email": "sagr@ne.ch",
      "telephone": "41 32 889 37 00",
      "active": true,
      "valid": true
    }
  },
  {
    "model": "ne_sop_api.Entity",
    "pk": 11,
    "fields": {
      "uuid": "43e17822-d8ed-4f8a-8fcf-3d5897520878",
      "name": "Service d’accompagnement et d’hébergement de l’adulte (SAHA)",
      "abbreviation": "SAHA",
      "type": 1,
      "description": "",
      "street": "Rue de Tivoli 28",
      "city": "Neuchâtel 2",
      "postalcode": "Case postale 1, 2002",
      "region": "Neuchâtel",
      "country": "Suisse",
      "website": "https://www.ne.ch/autorites/DECS/SAHA/Pages/accueil.aspx",
      "email": "saha@ne.ch",
      "telephone": "41 32 889 66 43",
      "active": true,
      "valid": true
    }
  },
  {
    "model": "ne_sop_api.Entity",
    "pk": 12,
    "fields": {
      "uuid": "28f2b8d1-35f9-4168-b23a-5470a2013b91",
      "name": "Service d'achat, de logistique et des imprimés (SALI)",
      "abbreviation": "SALI",
      "type": 1,
      "description": "",
      "street": "Rue du Plan 30",
      "city": "Neuchâtel 2",
      "postalcode": "Case postale 1, 2002",
      "region": "Neuchâtel",
      "country": "Suisse",
      "website": "https://www.ne.ch/autorites/CHAN/SALI/Pages/accueil.aspx",
      "email": "sali@ne.ch",
      "telephone": "41 32 889 60 30",
      "active": true,
      "valid": true
    }
  },
  {
    "model": "ne_sop_api.Entity",
    "pk": 13,
    "fields": {
      "uuid": "2d58a17b-b99c-404c-b2e7-88ddfcd36712",
      "name": "Service de l'action sociale (SASO)",
      "abbreviation": "SASO",
      "type": 1,
      "description": "",
      "street": "Rue de Tivoli 28",
      "city": "Neuchâtel 2",
      "postalcode": "Case postale 1, 2002",
      "region": "Neuchâtel",
      "country": "Suisse",
      "website": "https://www.ne.ch/autorites/DECS/SASO/Pages/accueil.aspx",
      "email": "Service.ActionSociale@ne.ch",
      "telephone": "41 32 889 60 89",
      "active": true,
      "valid": true
    }
  },
  {
    "model": "ne_sop_api.Entity",
    "pk": 14,
    "fields": {
      "uuid": "8cd2d590-81ae-42bc-8b74-b27f2ae481d4",
      "name": "Service des bâtiments (SBAT)",
      "abbreviation": "SBAT",
      "type": 1,
      "description": "",
      "street": "Rue de Tivoli 5",
      "city": "Neuchâtel 2",
      "postalcode": "Case postale, 2002",
      "region": "Neuchâtel",
      "country": "Suisse",
      "website": "https://www.ne.ch/autorites/DFS/SBAT/Pages/accueil.aspx",
      "email": "Service.Batiments@ne.ch",
      "telephone": "41 32 889 64 80",
      "active": true,
      "valid": true
    }
  },
  {
    "model": "ne_sop_api.Entity",
    "pk": 15,
    "fields": {
      "uuid": "178a09eb-d04d-4cc2-94d7-c3e3b53d0580",
      "name": "Service de l'aménagement du territoire (SCAT)",
      "abbreviation": "SCAT",
      "type": 1,
      "description": "",
      "street": "Rue de Tivoli 5",
      "city": "Neuchâtel 2",
      "postalcode": "Case postale, 2002",
      "region": "Neuchâtel",
      "country": "Suisse",
      "website": "https://www.ne.ch/autorites/DDTE/SCAT/Pages/accueil.aspx",
      "email": "Service.AmenagementTerritoire@ne.ch",
      "telephone": "41 32 889 67 40",
      "active": true,
      "valid": true
    }
  },
  {
    "model": "ne_sop_api.Entity",
    "pk": 16,
    "fields": {
      "uuid": "6ae879cb-5c47-4052-88ce-2591dd5c9a6b",
      "name": "Service de la consommation et des affaires vétérinaires (SCAV)",
      "abbreviation": "SCAV",
      "type": 1,
      "description": "",
      "street": "Rue Jehanne-de-Hochberg 5",
      "city": "Neuchâtel 2",
      "postalcode": "Case postale 1, 2002",
      "region": "Neuchâtel",
      "country": "Suisse",
      "website": "https://www.ne.ch/autorites/DDTE/SCAV/Pages/accueil.aspx",
      "email": "scav@ne.ch",
      "telephone": "41 32 889 68 30",
      "active": true,
      "valid": true
    }
  },
  {
    "model": "ne_sop_api.Entity",
    "pk": 17,
    "fields": {
      "uuid": "e996847b-cf10-494d-afc1-3a717919e05d",
      "name": "Service des contributions (SCCO)",
      "abbreviation": "SCCO",
      "type": 1,
      "description": "",
      "street": "Rue du Docteur-Coullery 5",
      "city": "La Chaux-de-Fonds",
      "postalcode": "2300",
      "region": "Neuchâtel",
      "country": "Suisse",
      "website": "https://www.ne.ch/autorites/DFS/SCCO/Pages/accueil.aspx",
      "email": "service.contributions@ne.ch",
      "telephone": "41 32 889 77 77",
      "active": true,
      "valid": true
    }
  },
  {
    "model": "ne_sop_api.Entity",
    "pk": 18,
    "fields": {
      "uuid": "4f16c1bd-732f-459c-88d6-d62a3cfd0754",
      "name": "Service de la culture (SCNE)",
      "abbreviation": "SCNE",
      "type": 1,
      "description": "",
      "street": "Château, Rue de la Collégiale 12",
      "city": "Neuchâtel 2",
      "postalcode": "Case postale 1, 2002",
      "region": "Neuchâtel",
      "country": "Suisse",
      "website": "https://www.ne.ch/autorites/DESC/SCNE/Pages/accueil.aspx",
      "email": "service.culture@ne.ch",
      "telephone": "41 32 889 69 08",
      "active": true,
      "valid": true
    }
  },
  {
    "model": "ne_sop_api.Entity",
    "pk": 19,
    "fields": {
      "uuid": "9382260a-0f95-4288-8235-df90a3450348",
      "name": "Service des communes (SCOM)",
      "abbreviation": "SCOM",
      "type": 1,
      "description": "",
      "street": "Rue de Tivoli 28",
      "city": "Neuchâtel 2",
      "postalcode": "Case postale 1, 2002",
      "region": "Neuchâtel",
      "country": "Suisse",
      "website": "https://www.ne.ch/autorites/DFS/SCOM/Pages/accueil.aspx",
      "email": "Service.Communes@ne.ch",
      "telephone": "41 32 889 66 50",
      "active": true,
      "valid": true
    }
  },
  {
    "model": "ne_sop_api.Entity",
    "pk": 20,
    "fields": {
      "uuid": "0b48f357-6a8e-4ee0-8eed-47bcb508f5f7",
      "name": "Service cantonal de la population (SCPO)",
      "abbreviation": "SCPO",
      "type": 1,
      "description": "",
      "street": "Rue de Tivoli 28",
      "city": "Neuchâtel 2",
      "postalcode": "Case postale 1, 2002",
      "region": "Neuchâtel",
      "country": "Suisse",
      "website": "https://www.ne.ch/autorites/DESC/SCPO/Pages/accueil.aspx",
      "email": "service.population@ne.ch",
      "telephone": "41 32 889 61 10",
      "active": true,
      "valid": true
    }
  },
  {
    "model": "ne_sop_api.Entity",
    "pk": 21,
    "fields": {
      "uuid": "991b5ef3-9ca0-4816-9056-26199e9419bb",
      "name": "Service de la santé publique (SCSP)",
      "abbreviation": "SCSP",
      "type": 1,
      "description": "",
      "street": "Rue de Tivoli 28",
      "city": "Neuchâtel 2",
      "postalcode": "Case postale 1, 2002",
      "region": "Neuchâtel",
      "country": "Suisse",
      "website": "https://www.ne.ch/autorites/DFS/SCSP/Pages/accueil.aspx",
      "email": "Service.SantePublique@ne.ch",
      "telephone": "41 32 889 62 00",
      "active": true,
      "valid": true
    }
  },
  {
    "model": "ne_sop_api.Entity",
    "pk": 22,
    "fields": {
      "uuid": "087fd563-6ded-4da9-ac33-57e1ad4a10e8",
      "name": "Service des transports (SCTR)",
      "abbreviation": "SCTR",
      "type": 1,
      "description": "",
      "street": "Rue de Tivoli 22",
      "city": "Neuchâtel",
      "postalcode": "2002",
      "region": "Neuchâtel",
      "country": "Suisse",
      "website": "https://www.ne.ch/autorites/DDTE/SCTR/Pages/accueil.aspx",
      "email": "service.transports@ne.ch",
      "telephone": "41 32 889 67 01",
      "active": true,
      "valid": true
    }
  },
  {
    "model": "ne_sop_api.Entity",
    "pk": 23,
    "fields": {
      "uuid": "ba88f780-be5b-4778-b1e3-1ab18321c4ed",
      "name": "Service de l'enseignement obligatoire (SEEO)",
      "abbreviation": "SEEO",
      "type": 1,
      "description": "",
      "street": "Rue de l'Ecluse 67",
      "city": "Neuchâtel 2",
      "postalcode": "Case postale 1, 2002",
      "region": "Neuchâtel",
      "country": "Suisse",
      "website": "https://www.ne.ch/autorites/DFDS/SEEO/Pages/accueil.aspx",
      "email": "Service.EnseignementObligatoire@ne.ch",
      "telephone": "41 32 889 69 20",
      "active": true,
      "valid": true
    }
  },
  {
    "model": "ne_sop_api.Entity",
    "pk": 24,
    "fields": {
      "uuid": "cac54165-45dd-45d7-9666-f2bfffcf7084",
      "name": "Service de l'emploi (SEMP)",
      "abbreviation": "SEMP",
      "type": 1,
      "description": "",
      "street": "Rue du Parc 119",
      "city": "La Chaux-de-Fonds",
      "postalcode": "2300",
      "region": "Neuchâtel",
      "country": "Suisse",
      "website": "https://www.ne.ch/autorites/DECS/SEMP/Pages/accueil.aspx",
      "email": "service.emploi@ne.ch",
      "telephone": "41 32 889 68 12",
      "active": true,
      "valid": true
    }
  },
  {
    "model": "ne_sop_api.Entity",
    "pk": 25,
    "fields": {
      "uuid": "704308ac-0823-42aa-abe2-1415d4feef88",
      "name": "Service de l'énergie et de l'environnement (SENE)",
      "abbreviation": "SENE",
      "type": 1,
      "description": "",
      "street": "Rue du Tombet 24",
      "city": "Peseux",
      "postalcode": "2034",
      "region": "Neuchâtel",
      "country": "Suisse",
      "website": "https://www.ne.ch/autorites/DDTE/SENE/Pages/accueil.aspx",
      "email": "sene@ne.ch",
      "telephone": "41 32 889 67 30",
      "active": true,
      "valid": true
    }
  },
  {
    "model": "ne_sop_api.Entity",
    "pk": 26,
    "fields": {
      "uuid": "e921a1b1-53c6-4220-884c-31f0809ded6c",
      "name": "Service des poursuites et faillites (SEPF)",
      "abbreviation": "SEPF",
      "type": 1,
      "description": "",
      "street": "Rue de Tivoli 28",
      "city": "Neuchâtel 2",
      "postalcode": "Case postale 1, 2002",
      "region": "Neuchâtel",
      "country": "Suisse",
      "website": "https://www.ne.ch/autorites/DESC/SEPF/Pages/accueil.aspx",
      "email": "Service.OP-OF@ne.ch",
      "telephone": "41 32 889 39 00",
      "active": true,
      "valid": true
    }
  },
  {
    "model": "ne_sop_api.Entity",
    "pk": 27,
    "fields": {
      "uuid": "649b2776-bcd6-41dc-8e05-4784b9a944fa",
      "name": "Service de la faune, des forêts et de la nature (SFFN)",
      "abbreviation": "SFFN",
      "type": 1,
      "description": "",
      "street": "Rue du Premier-Mars 11",
      "city": "Couvet",
      "postalcode": "2108",
      "region": "Neuchâtel",
      "country": "Suisse",
      "website": "https://www.ne.ch/autorites/DDTE/SFFN/Pages/accueil.aspx",
      "email": "sffn@ne.ch",
      "telephone": "41 32 889 67 60",
      "active": true,
      "valid": true
    }
  },
  {
    "model": "ne_sop_api.Entity",
    "pk": 28,
    "fields": {
      "uuid": "6aeb5df2-416e-443b-af96-0c546c8f60a2",
      "name": "Service financier (SFIN)",
      "abbreviation": "SFIN",
      "type": 1,
      "description": "",
      "street": "Rue de Tivoli 28",
      "city": "Neuchâtel 2",
      "postalcode": "Case postale 1, 2002",
      "region": "Neuchâtel",
      "country": "Suisse",
      "website": "https://www.ne.ch/autorites/dfs/sfin/Pages/service_financier.aspx",
      "email": "Service.Financier@ne.ch",
      "telephone": "41 32 889 64 10",
      "active": true,
      "valid": true
    }
  },
  {
    "model": "ne_sop_api.Entity",
    "pk": 29,
    "fields": {
      "uuid": "996e73c6-b861-481c-ad4b-8ec83fa330ea",
      "name": "Service des formations postobligatoires et de l'orientation (SFPO)",
      "abbreviation": "SFPO",
      "type": 1,
      "description": "",
      "street": "Espacité 1",
      "city": "La Chaux-de-Fonds",
      "postalcode": "2300",
      "region": "Neuchâtel",
      "country": "Suisse",
      "website": "https://www.ne.ch/autorites/DFDS/SFPO/Pages/accueil.aspx",
      "email": "sfpo@ne.ch",
      "telephone": "41 32 889 69 40",
      "active": true,
      "valid": true
    }
  },
  {
    "model": "ne_sop_api.Entity",
    "pk": 30,
    "fields": {
      "uuid": "0c6983d6-ad06-4e4d-b399-a57be9a16195",
      "name": "Service de la géomatique et du registre foncier (SGRF)",
      "abbreviation": "SGRF",
      "type": 1,
      "description": "",
      "street": "Rue de Tivoli 22",
      "city": "Neuchâtel 2",
      "postalcode": "Case postale 1, 2002",
      "region": "Neuchâtel",
      "country": "Suisse",
      "website": "https://www.ne.ch/autorites/DDTE/SGRF/Pages/accueil.aspx",
      "email": "sgrf@ne.ch",
      "telephone": "41 32 889 67 50",
      "active": true,
      "valid": true
    }
  },
  {
    "model": "ne_sop_api.Entity",
    "pk": 31,
    "fields": {
      "uuid": "efebd3ed-6150-4d4d-b3e9-7921bc68377f",
      "name": "Service informatique de l'entité neuchâteloise (SIEN)",
      "abbreviation": "SIEN",
      "type": 1,
      "description": "",
      "street": "Avenue des Cadolles 7",
      "city": "Neuchâtel 2",
      "postalcode": "Case postale 1, 2002",
      "region": "Neuchâtel",
      "country": "Suisse",
      "website": "https://www.ne.ch/autorites/DFDS/SIEN/Pages/accueil.aspx",
      "email": "SIEN@ne.ch",
      "telephone": "41 32 889 64 70",
      "active": true,
      "valid": true
    }
  },
  {
    "model": "ne_sop_api.Entity",
    "pk": 32,
    "fields": {
      "uuid": "17156473-95db-4d83-80ad-197116c11d05",
      "name": "Service juridique (SJEN)",
      "abbreviation": "SJEN",
      "type": 1,
      "description": "",
      "street": "Château, Rue de la Collégiale 12",
      "city": "Neuchâtel 2",
      "postalcode": "Case postale 1, 2002",
      "region": "Neuchâtel",
      "country": "Suisse",
      "website": "https://www.ne.ch/autorites/desc/sjen/Pages/accueil.aspx",
      "email": "Service.Juridique@ne.ch",
      "telephone": "41 32 889 64 40",
      "active": true,
      "valid": true
    }
  },
  {
    "model": "ne_sop_api.Entity",
    "pk": 33,
    "fields": {
      "uuid": "1dbc4841-dfb9-4809-a8e3-c9d36b35c5ae",
      "name": "Service des migrations (SMIG)",
      "abbreviation": "SMIG",
      "type": 1,
      "description": "",
      "street": "Rue de Tivoli 28",
      "city": "Neuchâtel 2",
      "postalcode": "Case postale 1, 2002",
      "region": "Neuchâtel",
      "country": "Suisse",
      "website": "https://www.ne.ch/autorites/DECS/SMIG/Pages/accueil.aspx",
      "email": "smig@ne.ch",
      "telephone": "41 32 889 63 10",
      "active": true,
      "valid": true
    }
  },
  {
    "model": "ne_sop_api.Entity",
    "pk": 34,
    "fields": {
      "uuid": "6d0de5c1-45b5-4bd7-9a9d-0456f0d2719b",
      "name": "Service de protection de l'adulte et de la jeunesse (SPAJ)",
      "abbreviation": "SPAJ",
      "type": 1,
      "description": "",
      "street": "Faubourg de l'Hôpital 34",
      "city": "Neuchâtel",
      "postalcode": "2000",
      "region": "Neuchâtel",
      "country": "Suisse",
      "website": "https://www.ne.ch/autorites/DFDS/SPAJ/Pages/accueil.aspx",
      "email": "SPAJ@ne.ch",
      "telephone": "41 32 889 66 67",
      "active": true,
      "valid": true
    }
  },
  {
    "model": "ne_sop_api.Entity",
    "pk": 35,
    "fields": {
      "uuid": "76ffcbae-6b2e-414b-90b0-ae66c5282736",
      "name": "Service des ponts et chaussées (SPCH)",
      "abbreviation": "SPCH",
      "type": 1,
      "description": "",
      "street": "Rue J.-L. Pourtalès 13",
      "city": "Neuchâtel 2",
      "postalcode": "Case postale 1, 2002",
      "region": "Neuchâtel",
      "country": "Suisse",
      "website": "https://www.ne.ch/autorites/DDTE/SPCH/Pages/accueil.aspx",
      "email": "Service.PontsChaussees@ne.ch",
      "telephone": "41 32 889 67 10",
      "active": true,
      "valid": true
    }
  },
  {
    "model": "ne_sop_api.Entity",
    "pk": 36,
    "fields": {
      "uuid": "d40eb3fc-d8de-4fd5-8ac5-7abf69e1d11b",
      "name": "Service pénitentiaire (SPNE)",
      "abbreviation": "SPNE",
      "type": 1,
      "description": "",
      "street": "Rue de la Promenade 20",
      "city": "La Chaux-de-Fonds",
      "postalcode": "2300",
      "region": "Neuchâtel",
      "country": "Suisse",
      "website": "https://www.ne.ch/autorites/desc/spne/Pages/accueil.aspx",
      "email": "Service.Penitentiaire@ne.ch",
      "telephone": "41 32 889 61 30",
      "active": true,
      "valid": true
    }
  },
  {
    "model": "ne_sop_api.Entity",
    "pk": 37,
    "fields": {
      "uuid": "65d2eb83-f4aa-404c-a175-02864ab43485",
      "name": "Service des ressources humaines (SRHE)",
      "abbreviation": "SRHE",
      "type": 1,
      "description": "",
      "street": "Rue de Tivoli 28",
      "city": "Neuchâtel 2",
      "postalcode": "Case postale 1, 2002",
      "region": "Neuchâtel",
      "country": "Suisse",
      "website": "https://www.ne.ch/autorites/DESC/SRHE/Pages/accueil.aspx",
      "email": "srhe@ne.ch",
      "telephone": "41 32 889 64 50",
      "active": true,
      "valid": true
    }
  },
  {
    "model": "ne_sop_api.Entity",
    "pk": 38,
    "fields": {
      "uuid": "f7c6c1d0-3c21-4d0f-a296-100f0d82fc11",
      "name": "Service de la sécurité civile et militaire (SSCM)",
      "abbreviation": "SSCM",
      "type": 1,
      "description": "",
      "street": "Route de l'Arsenal 2",
      "city": "Colombier",
      "postalcode": "2013",
      "region": "Neuchâtel",
      "country": "Suisse",
      "website": "https://www.ne.ch/autorites/DESC/SSCM/Pages/accueil.aspx",
      "email": "Service.SecuriteCivileMilitaire@ne.ch",
      "telephone": "41 32 889 63 31",
      "active": true,
      "valid": true
    }
  },
  {
    "model": "ne_sop_api.Entity",
    "pk": 39,
    "fields": {
      "uuid": "9fdf3ae5-6b68-448f-b4f4-972784f01e8d",
      "name": "Service cantonal des sports (SSPO)",
      "abbreviation": "SSPO",
      "type": 1,
      "description": "",
      "street": "Rue du Cygne 8",
      "city": "La Chaux-de-Fonds",
      "postalcode": "2300",
      "region": "Neuchâtel",
      "country": "Suisse",
      "website": "https://www.ne.ch/autorites/DFDS/SSPO/Pages/accueil.aspx",
      "email": "service.sports@ne.ch",
      "telephone": "41 32 889 69 11",
      "active": true,
      "valid": true
    }
  },
  {
    "model": "ne_sop_api.Entity",
    "pk": 40,
    "fields": {
      "uuid": "1dcc8d42-47f0-4c5d-9f43-10f4b1b02a1e",
      "name": "Service de statistique (STAT)",
      "abbreviation": "STAT",
      "type": 1,
      "description": "",
      "street": "Rue de Tivoli 28",
      "city": "Neuchâtel 2",
      "postalcode": "Case postale 1, 2002",
      "region": "Neuchâtel",
      "country": "Suisse",
      "website": "https://www.ne.ch/autorites/DFS/STAT/Pages/accueil.aspx",
      "email": "stat@ne.ch",
      "telephone": "41 32 889 68 22",
      "active": true,
      "valid": true
    }
  }
]
